sanitize_cli/__init__.py
sanitize_cli/cli.py
sanitize_comments_cli-0.1.0.dist-info/licenses/LICENSE
sanitize_comments_cli-0.1.0.dist-info/METADATA
sanitize_comments_cli-0.1.0.dist-info/WHEEL
sanitize_comments_cli-0.1.0.dist-info/entry_points.txt
sanitize_comments_cli-0.1.0.dist-info/top_level.txt
sanitize_comments_cli-0.1.0.dist-info/RECORD
