Metadata-Version: 2.4
Name: sanitize-comments-cli
Version: 0.1.0
Summary: CLI tool to remove comments from source files.
Author-email: Rohinish <singhrohinish09@gmail.com>
License: MIT License
Project-URL: Homepage, https://github.com/rohinish404/sanitize_cli
Project-URL: Repository, https://github.com/rohinish404/sanitize_cli
Keywords: cli,comments,code,cleanup,developer-tools,utility,tokenizer,pygments
Classifier: Development Status :: 4 - Beta
Classifier: Environment :: Console
Classifier: Intended Audience :: Developers
Classifier: License :: OSI Approved :: MIT License
Classifier: Operating System :: OS Independent
Classifier: Programming Language :: Python :: 3
Classifier: Programming Language :: Python :: 3.8
Classifier: Programming Language :: Python :: 3.9
Classifier: Programming Language :: Python :: 3.10
Classifier: Programming Language :: Python :: 3.11
Classifier: Programming Language :: Python :: 3.12
Classifier: Topic :: Software Development :: Libraries :: Python Modules
Classifier: Topic :: Text Processing
Classifier: Topic :: Utilities
Requires-Python: >=3.8
License-File: LICENSE
Requires-Dist: pygments>=2.9.0
Dynamic: license-file
